niqe/__init__.py
niqe/main.py
tapan_niqe/__init__.py
tapan_niqe/main.py
niqe-0.1.1.dist-info/LICENSE
niqe-0.1.1.dist-info/METADATA
niqe-0.1.1.dist-info/WHEEL
niqe-0.1.1.dist-info/top_level.txt
niqe-0.1.1.dist-info/RECORD
