Metadata-Version: 2.1
Name: niqe
Version: 0.1.1
Summary: read
Author: tapan
Author-email: tapan5356@gmail.com
License: MIT
Platform: UNKNOWN
Requires-Python: >=3
License-File: LICENSE
Requires-Dist: numpy
Requires-Dist: opencv-python
Requires-Dist: scipy
Requires-Dist: scikit-image
